sparc_me/__init__.py
sparc_me/core/__init__.py
sparc_me/core/api_tools.py
sparc_me/core/dataset.py
sparc_me/core/metadata.py
sparc_me/core/schema.py
sparc_me/core/utils.py
sparc_me/resources/templates/version_1_2_3/schema.json
sparc_me/resources/templates/version_1_2_3/schema.xlsx
sparc_me/resources/templates/version_1_2_3/DatasetTemplate/CHANGES
sparc_me/resources/templates/version_1_2_3/DatasetTemplate/README
sparc_me/resources/templates/version_1_2_3/DatasetTemplate/dataset_description.xlsx
sparc_me/resources/templates/version_1_2_3/DatasetTemplate/samples.xlsx
sparc_me/resources/templates/version_1_2_3/DatasetTemplate/subjects.xlsx
sparc_me/resources/templates/version_1_2_3/DatasetTemplate/submission.xlsx
sparc_me/resources/templates/version_1_2_3/DatasetTemplate/code/README
sparc_me/resources/templates/version_1_2_3/DatasetTemplate/code/manifest.xlsx
sparc_me/resources/templates/version_1_2_3/DatasetTemplate/derivative/README
sparc_me/resources/templates/version_1_2_3/DatasetTemplate/docs/README
sparc_me/resources/templates/version_1_2_3/DatasetTemplate/docs/manifest.xlsx
sparc_me/resources/templates/version_1_2_3/DatasetTemplate/primary/README
sparc_me/resources/templates/version_1_2_3/DatasetTemplate/primary/manifest.xlsx
sparc_me/resources/templates/version_1_2_3/DatasetTemplate/primary/pool-1/plog.xlsx
sparc_me/resources/templates/version_1_2_3/DatasetTemplate/primary/pool-1/perf-1/manifest.xlsx
sparc_me/resources/templates/version_1_2_3/DatasetTemplate/primary/pool-1/perf-2/manifest.xlsx
sparc_me/resources/templates/version_1_2_3/DatasetTemplate/primary/pool-2/manifest.xlsx
sparc_me/resources/templates/version_1_2_3/DatasetTemplate/primary/sub-1/sam-1/plog.xlsx
sparc_me/resources/templates/version_1_2_3/DatasetTemplate/primary/sub-1/sam-1/perf-1/manifest.xlsx
sparc_me/resources/templates/version_1_2_3/DatasetTemplate/primary/sub-1/sam-1/perf-2/manifest.xlsx
sparc_me/resources/templates/version_1_2_3/DatasetTemplate/primary/sub-1/sam-2/manifest.xlsx
sparc_me-3.0.2.dist-info/LICENSE
sparc_me-3.0.2.dist-info/METADATA
sparc_me-3.0.2.dist-info/WHEEL
sparc_me-3.0.2.dist-info/top_level.txt
sparc_me-3.0.2.dist-info/RECORD
