Metadata-Version: 2.1
Name: sparc-me
Version: 3.0.2
Summary: A python tool to explore, enhance, and expand SPARC datasets and their descriptions in accordance with FAIR principles.
Author: Thiranja Prasad Babarenda Gamage, Chinchien Lin, Savindi Wijenayaka, Michael Hoffman, Linkun Gao, Haribalan Kumar
License: Apache-2.0
License-File: LICENSE
Requires-Dist: pandas
Requires-Dist: styleframe
Requires-Dist: xlrd
Requires-Dist: openpyxl
Requires-Dist: jsonschema
Requires-Dist: requests
